setup.py
django_referrals.egg-info/PKG-INFO
django_referrals.egg-info/SOURCES.txt
django_referrals.egg-info/dependency_links.txt
django_referrals.egg-info/not-zip-safe
django_referrals.egg-info/requires.txt
django_referrals.egg-info/top_level.txt
referrals/__init__.py
referrals/admin.py
referrals/forms.py
referrals/models.py
referrals/signals.py
referrals/urls.py
referrals/utils.py
referrals/views.py
referrals/migrations/0001_initial.py
referrals/migrations/__init__.py