Metadata-Version: 1.0
Name: django-referrals
Version: 0.1
Summary: Tracking user referrals in a Django project
Home-page: http://github.com/tivix/django-referrals
Author: Matthew Farver
Author-email: mfarver@tivix.com
License: UNKNOWN
Platform: UNKNOWN
Classifier: Framework :: Django
Classifier: Intended Audience :: Developers
Classifier: Intended Audience :: System Administrators
Classifier: Operating System :: OS Independent
Classifier: Topic :: Software Development
